date_to.py
date_to-1.2.1.dist-info/LICENSE
date_to-1.2.1.dist-info/WHEEL
date_to-1.2.1.dist-info/METADATA
date_to-1.2.1.dist-info/RECORD
