Metadata-Version: 2.1
Name: date_to
Version: 1.2.1
Summary: One friendly python function for parsing and converting to and between datetime.datetime, int, and string objects
Author-email: Arnaud van Haaster <dont@me.please>
Requires-Python: >=3.10
Classifier: Intended Audience :: Developers
Classifier: License :: OSI Approved :: The Unlicense (Unlicense)
Classifier: Development Status :: 5 - Production/Stable
Classifier: Natural Language :: English
Classifier: Programming Language :: Python :: 3 :: Only
Classifier: Programming Language :: Python :: 3.10
Classifier: Programming Language :: Python :: 3.11
Classifier: Topic :: Software Development :: Libraries :: Python Modules
Classifier: Operating System :: OS Independent
Requires-Dist: dateparser>=1.1.2
Project-URL: Documentation, https://github.com/ahaaster/date-to/blob/master/README.md
Project-URL: Home, https://github.com/ahaaster/date-to
Project-URL: Source, https://github.com/ahaaster/date-to/blob/master/date_to.py
